{
  "num": 1,
  "ids":
  [
    "a001550"
  ],
  "objects":
  {
    "a001550":
    {
      "object": "a001550",
      "packed": "a001550",
      "created": 2460945.65391,
      "created iso": "2025-09-27T03:41:37Z",
      "Find_Orb_version": 2460934.50000,
      "Find_Orb_version_iso": "2025-09-16T00:00:00Z",
      "elements":
      {
        "central body": "Sun",
        "frame": "J2000 ecliptic",
        "reference": "Find_Orb",
        "epoch_iso": "2022-09-01T00:00:00Z",
        "epoch":  2459823.50000000,
        "P": 2060.1589844592495, "P sigma": 2.59,
        "M": 301.8010689779962, "M sigma": 2.3,
        "n":   0.1747437953651, "n sigma": 0.000219,
        "a":   3.1686057536521, "a sigma": 0.00265,
        "e":   0.2078700213793, "e sigma": 0.00134,
        "q":   2.5099476078979, "q sigma": 0.00254,
        "Q":   3.8272638994063, "Q sigma": 0.00724,
        "i":   1.9293263143713, "i sigma": 0.035,
        "arg_per":  292.4674768344371, "arg_per sigma":  2.1,
        "asc_node": 122.6059552382045, "asc_node sigma": 0.46,
        "Tp": 2460156.55291842, "Tp sigma": 13.3,
        "Tp_iso": "2023-07-31T01:16:12.151Z",
        "H":  16.12,
        "G":   0.15,
        "rms_residual": 0.046365,
        "weighted_rms_residual": 0.2318,
        "n_resids": 22,
        "U": 7.4017,
        "p_NEO": 0.0000,
        "MOIDs":
        {
          "Mercury" : 2.197114,
          "Venus" : 1.787781,
          "Earth" : 1.521870,
          "Mars" : 1.003939,
          "Jupiter" : 1.543260,
          "Saturn" : 5.990073,
          "Uranus" : 14.706404,
          "Neptune" : 26.495299 
        }
      },
      "observations":
      {
        "count": 11,
        "used": 11,
        "earliest": 2459813.91620800,
        "latest": 2459823.95572000,
        "earliest iso": "2022-08-22T09:59:20.371Z",
        "latest iso": "2022-09-01T10:56:14.208Z",
        "earliest_used": 2459813.91620800,
        "latest_used": 2459823.95572000,
        "earliest_used iso": "2022-08-22T09:59:20.371Z",
        "latest_used iso": "2022-09-01T10:56:14.208Z",
        "earliest_unbanned": 2459813.91620800,
        "latest_unbanned": 2459823.95572000,
        "earliest_unbanned iso": "2022-08-22T09:59:20.371Z",
        "latest_unbanned iso": "2022-09-01T10:56:14.208Z",
        "residuals":
        [
          {"JD": 2459813.916208, "iso date": "2022-08-22T09:59:20.371Z", "obscode": "F51",
                 "RA" : 336.237696, "Dec": -11.462567,
                 "dRA" : 0.009, "dDec": -0.109, "dTime": 4.076, "cross": -0.104,
                 "reference" : "     ",  "packed" : "     a001550",
                 "sigma_1" : 0.200000,
                 "sigma_2" : 0.200000,
                 "normalized_resid_1" : -0.175471,
                 "normalized_resid_2" : 0.519403,
                 "posn_sigma_theta" : 0.000000,
                 "RAMotion" : -0.4744,
                 "decMotion" : -0.2058,
                 "TotalMotion" : 0.5171,
                 "PAMotion" : 246.55, "dMag" : 0.03, "MagObs" : 20.30,
                 "MagBand" : "w", "MagSigma" : 0.5000,
                 "net" : " ",
                 "note1" : " ",
                 "note2" : "C",
                 "discovery_asterisk" : " ",
                 "flags" : 0,
                 "incl" : 1,
                 "ecliptic_lon" : 333.799760,
                 "ecliptic_lat" : -1.446546,
                 "earth_ecliptic_lon" : 330.384205 },
          {"JD": 2459813.928701, "iso date": "2022-08-22T10:17:19.766Z", "obscode": "F51",
                 "RA" : 336.235258, "Dec": -11.463547,
                 "dRA" : -0.0643, "dDec": 0.0562, "dTime": 4.258, "cross": 0.0771,
                 "reference" : "     ",  "packed" : "     a001550",
                 "sigma_1" : 0.200000,
                 "sigma_2" : 0.200000,
                 "normalized_resid_1" : -0.183392,
                 "normalized_resid_2" : -0.385413,
                 "posn_sigma_theta" : 0.000000,
                 "RAMotion" : -0.4747,
                 "decMotion" : -0.2055,
                 "TotalMotion" : 0.5173,
                 "PAMotion" : 246.59, "dMag" : 0.14, "MagObs" : 20.40,
                 "MagBand" : "w", "MagSigma" : 0.5000,
                 "net" : " ",
                 "note1" : " ",
                 "note2" : "C",
                 "discovery_asterisk" : " ",
                 "flags" : 0,
                 "incl" : 1,
                 "ecliptic_lon" : 333.797178,
                 "ecliptic_lat" : -1.446590,
                 "earth_ecliptic_lon" : 330.396518 },
          {"JD": 2459813.941180, "iso date": "2022-08-22T10:35:17.952Z", "obscode": "F51",
                 "RA" : 336.232879, "Dec": -11.464592,
                 "dRA" : 0.0628, "dDec": -0.0175, "dTime": -5.884, "cross": -0.0410,
                 "reference" : "     ",  "packed" : "     a001550",
                 "sigma_1" : 0.200000,
                 "sigma_2" : 0.200000,
                 "normalized_resid_1" : 0.253417,
                 "normalized_resid_2" : 0.205176,
                 "posn_sigma_theta" : 0.000000,
                 "RAMotion" : -0.4749,
                 "decMotion" : -0.2052,
                 "TotalMotion" : 0.5173,
                 "PAMotion" : 246.63, "dMag" : 0.04, "MagObs" : 20.30,
                 "MagBand" : "w", "MagSigma" : 0.5000,
                 "net" : " ",
                 "note1" : " ",
                 "note2" : "C",
                 "discovery_asterisk" : " ",
                 "flags" : 0,
                 "incl" : 1,
                 "ecliptic_lon" : 333.794625,
                 "ecliptic_lat" : -1.446713,
                 "earth_ecliptic_lon" : 330.408818 },
          {"JD": 2459813.953647, "iso date": "2022-08-22T10:53:15.100Z", "obscode": "F51",
                 "RA" : 336.230446, "Dec": -11.465589,
                 "dRA" : -0.0070, "dDec": 0.0702, "dTime": -2.478, "cross": 0.0672,
                 "reference" : "     ",  "packed" : "     a001550",
                 "sigma_1" : 0.200000,
                 "sigma_2" : 0.200000,
                 "normalized_resid_1" : 0.106719,
                 "normalized_resid_2" : -0.336160,
                 "posn_sigma_theta" : 0.000000,
                 "RAMotion" : -0.4749,
                 "decMotion" : -0.2049,
                 "TotalMotion" : 0.5173,
                 "PAMotion" : 246.66, "dMag" : -0.06, "MagObs" : 20.20,
                 "MagBand" : "w", "MagSigma" : 0.5000,
                 "net" : " ",
                 "note1" : " ",
                 "note2" : "C",
                 "discovery_asterisk" : " ",
                 "flags" : 0,
                 "incl" : 1,
                 "ecliptic_lon" : 333.792040,
                 "ecliptic_lat" : -1.446774,
                 "earth_ecliptic_lon" : 330.421105 },
          {"JD": 2459819.903803, "iso date": "2022-08-28T09:41:28.579Z", "obscode": "F52",
                 "RA" : 335.105812, "Dec": -11.953514,
                 "dRA" : 0.0126, "dDec": -0.0322, "dTime": 0.108, "cross": -0.0346,
                 "reference" : "     ",  "packed" : "     a001550",
                 "sigma_1" : 0.200000,
                 "sigma_2" : 0.200000,
                 "normalized_resid_1" : -0.004730,
                 "normalized_resid_2" : 0.172835,
                 "posn_sigma_theta" : 0.000000,
                 "RAMotion" : -0.4855,
                 "decMotion" : -0.2047,
                 "TotalMotion" : 0.5269,
                 "PAMotion" : 247.14, "dMag" : -0.07, "MagObs" : 20.10,
                 "MagBand" : "w", "MagSigma" : 0.5000,
                 "net" : " ",
                 "note1" : " ",
                 "note2" : "C",
                 "discovery_asterisk" : " ",
                 "flags" : 0,
                 "incl" : 1,
                 "ecliptic_lon" : 332.588442,
                 "ecliptic_lat" : -1.502241,
                 "earth_ecliptic_lon" : 336.285633 },
          {"JD": 2459819.917288, "iso date": "2022-08-28T10:00:53.683Z", "obscode": "F52",
                 "RA" : 335.103146, "Dec": -11.954608,
                 "dRA" : 0.0397, "dDec": -0.0052, "dTime": -3.939, "cross": -0.0202,
                 "reference" : "     ",  "packed" : "     a001550",
                 "sigma_1" : 0.200000,
                 "sigma_2" : 0.200000,
                 "normalized_resid_1" : 0.172790,
                 "normalized_resid_2" : 0.100913,
                 "posn_sigma_theta" : 0.000000,
                 "RAMotion" : -0.4857,
                 "decMotion" : -0.2043,
                 "TotalMotion" : 0.5270,
                 "PAMotion" : 247.18, "dMag" : -0.07, "MagObs" : 20.10,
                 "MagBand" : "w", "MagSigma" : 0.5000,
                 "net" : " ",
                 "note1" : " ",
                 "note2" : "C",
                 "discovery_asterisk" : " ",
                 "flags" : 0,
                 "incl" : 1,
                 "ecliptic_lon" : 332.585613,
                 "ecliptic_lat" : -1.502320,
                 "earth_ecliptic_lon" : 336.298924 },
          {"JD": 2459819.930784, "iso date": "2022-08-28T10:20:19.737Z", "obscode": "F52",
                 "RA" : 335.100442, "Dec": -11.955686,
                 "dRA" : -0.0548, "dDec": 0.0786, "dTime": 2.294, "cross": 0.0937,
                 "reference" : "     ",  "packed" : "     a001550",
                 "sigma_1" : 0.200000,
                 "sigma_2" : 0.200000,
                 "normalized_resid_1" : -0.100643,
                 "normalized_resid_2" : -0.468326,
                 "posn_sigma_theta" : 0.000000,
                 "RAMotion" : -0.4858,
                 "decMotion" : -0.2040,
                 "TotalMotion" : 0.5269,
                 "PAMotion" : 247.22, "dMag" : -0.07, "MagObs" : 20.10,
                 "MagBand" : "w", "MagSigma" : 0.5000,
                 "net" : " ",
                 "note1" : " ",
                 "note2" : "C",
                 "discovery_asterisk" : " ",
                 "flags" : 0,
                 "incl" : 1,
                 "ecliptic_lon" : 332.582756,
                 "ecliptic_lat" : -1.502371,
                 "earth_ecliptic_lon" : 336.312226 },
          {"JD": 2459819.944264, "iso date": "2022-08-28T10:39:44.409Z", "obscode": "F52",
                 "RA" : 335.097783, "Dec": -11.956817,
                 "dRA" : 0.0009, "dDec": -0.0389, "dTime": 1.619, "cross": -0.0362,
                 "reference" : "     ",  "packed" : "     a001550",
                 "sigma_1" : 0.200000,
                 "sigma_2" : 0.200000,
                 "normalized_resid_1" : -0.070975,
                 "normalized_resid_2" : 0.181233,
                 "posn_sigma_theta" : 0.000000,
                 "RAMotion" : -0.4857,
                 "decMotion" : -0.2037,
                 "TotalMotion" : 0.5267,
                 "PAMotion" : 247.25, "dMag" : 0.03, "MagObs" : 20.20,
                 "MagBand" : "w", "MagSigma" : 0.5000,
                 "net" : " ",
                 "note1" : " ",
                 "note2" : "C",
                 "discovery_asterisk" : " ",
                 "flags" : 0,
                 "incl" : 1,
                 "ecliptic_lon" : 332.579921,
                 "ecliptic_lat" : -1.502486,
                 "earth_ecliptic_lon" : 336.325512 },
          {"JD": 2459823.931984, "iso date": "2022-09-01T10:22:03.417Z", "obscode": "F51",
                 "RA" : 334.338400, "Dec": -12.278222,
                 "dRA" : 0.0073, "dDec": -0.0106, "dTime": -0.314, "cross": -0.0126,
                 "reference" : "     ",  "packed" : "     a001550",
                 "sigma_1" : 0.200000,
                 "sigma_2" : 0.200000,
                 "normalized_resid_1" : 0.013634,
                 "normalized_resid_2" : 0.062817,
                 "posn_sigma_theta" : 0.000000,
                 "RAMotion" : -0.4821,
                 "decMotion" : -0.1984,
                 "TotalMotion" : 0.5213,
                 "PAMotion" : 247.62, "dMag" : 0.02, "MagObs" : 20.30,
                 "MagBand" : "w", "MagSigma" : 0.5000,
                 "net" : " ",
                 "note1" : " ",
                 "note2" : "C",
                 "discovery_asterisk" : " ",
                 "flags" : 0,
                 "incl" : 1,
                 "ecliptic_lon" : 331.771256,
                 "ecliptic_lat" : -1.535228,
                 "earth_ecliptic_lon" : 340.255845 },
          {"JD": 2459823.943851, "iso date": "2022-09-01T10:39:08.726Z", "obscode": "F51",
                 "RA" : 334.336058, "Dec": -12.279172,
                 "dRA" : -0.0036, "dDec": -0.0456, "dTime": 2.381, "cross": -0.0408,
                 "reference" : "     ",  "packed" : "     a001550",
                 "sigma_1" : 0.200000,
                 "sigma_2" : 0.200000,
                 "normalized_resid_1" : -0.103294,
                 "normalized_resid_2" : 0.203995,
                 "posn_sigma_theta" : 0.000000,
                 "RAMotion" : -0.4819,
                 "decMotion" : -0.1981,
                 "TotalMotion" : 0.5210,
                 "PAMotion" : 247.65, "dMag" : 0.02, "MagObs" : 20.30,
                 "MagBand" : "w", "MagSigma" : 0.5000,
                 "net" : " ",
                 "note1" : " ",
                 "note2" : "C",
                 "discovery_asterisk" : " ",
                 "flags" : 0,
                 "incl" : 1,
                 "ecliptic_lon" : 331.768779,
                 "ecliptic_lat" : -1.535294,
                 "earth_ecliptic_lon" : 340.267541 },
          {"JD": 2459823.955720, "iso date": "2022-09-01T10:56:14.208Z", "obscode": "F51",
                 "RA" : 334.333721, "Dec": -12.280083,
                 "dRA" : -0.0028, "dDec": 0.0546, "dTime": -2.096, "cross": 0.0516,
                 "reference" : "     ",  "packed" : "     a001550",
                 "sigma_1" : 0.200000,
                 "sigma_2" : 0.200000,
                 "normalized_resid_1" : 0.090840,
                 "normalized_resid_2" : -0.258025,
                 "posn_sigma_theta" : 0.000000,
                 "RAMotion" : -0.4816,
                 "decMotion" : -0.1978,
                 "TotalMotion" : 0.5206,
                 "PAMotion" : 247.67, "dMag" : 0.01, "MagObs" : 20.30,
                 "MagBand" : "w", "MagSigma" : 0.5000,
                 "net" : " ",
                 "note1" : " ",
                 "note2" : "C",
                 "discovery_asterisk" : " ",
                 "flags" : 0,
                 "incl" : 1,
                 "ecliptic_lon" : 331.766319,
                 "ecliptic_lat" : -1.535326,
                 "earth_ecliptic_lon" : 340.279239 } 
        ]
      },
      "ephemeris":
      {
        "obscode": "500",
        "packed": "a001550",
        "count": 10,
        "start": 2460945.500000,
        "step": 1.000000000,
        "n_steps": 10,
        "start iso": "2025-09-27T00:00:00.000Z",
        "entries":
        {
          "0": {"JD": 2460945.500000000, "ISO_time": "2025-09-27T00:00:00Z", "RA": 200.43393789487, "RA60": "13 21 44.145", "Dec": -6.95977290664, "Dec60": "-06 57 35.18", "delta": 4.648425653065, "r": 3.706370457723, "elong": 17.75401, "mag": 22.707, "sigPos": 2988.808, "sigPA": 110 },
          "1": {"JD": 2460946.500000000, "ISO_time": "2025-09-28T00:00:00Z", "RA": 200.71697291711, "RA60": "13 22 52.074", "Dec": -7.07352373638, "Dec60": "-07 04 24.69", "delta": 4.653601434117, "r": 3.707359955510, "elong": 17.07863, "mag": 22.700, "sigPos": 2992.471, "sigPA": 110 },
          "2": {"JD": 2460947.500000000, "ISO_time": "2025-09-29T00:00:00Z", "RA": 201.00052247156, "RA60": "13 24 00.125", "Dec": -7.18715074664, "Dec60": "-07 11 13.74", "delta": 4.658603526306, "r": 3.708345530620, "elong": 16.40333, "mag": 22.694, "sigPos": 2996.191, "sigPA": 110 },
          "3": {"JD": 2460948.500000000, "ISO_time": "2025-09-30T00:00:00Z", "RA": 201.28456995401, "RA60": "13 25 08.297", "Dec": -7.30064278546, "Dec60": "-07 18 02.31", "delta": 4.663431460450, "r": 3.709327180453, "elong": 15.72813, "mag": 22.686, "sigPos": 2999.968, "sigPA": 110 },
          "4": {"JD": 2460949.500000000, "ISO_time": "2025-10-01T00:00:00Z", "RA": 201.56909917690, "RA60": "13 26 16.584", "Dec": -7.41398899523, "Dec60": "-07 24 50.36", "delta": 4.668084820594, "r": 3.710304902424, "elong": 15.05304, "mag": 22.679, "sigPos": 3003.802, "sigPA": 110 },
          "5": {"JD": 2460950.500000000, "ISO_time": "2025-10-02T00:00:00Z", "RA": 201.85409445378, "RA60": "13 27 24.983", "Dec": -7.52717885224, "Dec60": "-07 31 37.84", "delta": 4.672563242419, "r": 3.711278693964, "elong": 14.37808, "mag": 22.672, "sigPos": 3007.691, "sigPA": 110 },
          "6": {"JD": 2460951.500000000, "ISO_time": "2025-10-03T00:00:00Z", "RA": 202.13954071978, "RA60": "13 28 33.490", "Dec": -7.64020222018, "Dec60": "-07 38 24.73", "delta": 4.676866409394, "r": 3.712248552520, "elong": 13.70328, "mag": 22.664, "sigPos": 3011.637, "sigPA": 110 },
          "7": {"JD": 2460952.500000000, "ISO_time": "2025-10-04T00:00:00Z", "RA": 202.42542368304, "RA60": "13 29 42.102", "Dec": -7.75304941179, "Dec60": "-07 45 10.98", "delta": 4.680994044067, "r": 3.713214475555, "elong": 13.02867, "mag": 22.655, "sigPos": 3015.639, "sigPA": 110 },
          "8": {"JD": 2460953.500000000, "ISO_time": "2025-10-05T00:00:00Z", "RA": 202.71172998315, "RA60": "13 30 50.815", "Dec": -7.86571124392, "Dec60": "-07 51 56.56", "delta": 4.684945891760, "r": 3.714176460547, "elong": 12.35428, "mag": 22.647, "sigPos": 3019.696, "sigPA": 109 },
          "9": {"JD": 2460954.500000000, "ISO_time": "2025-10-06T00:00:00Z", "RA": 202.99844730805, "RA60": "13 31 59.627", "Dec": -7.97817906037, "Dec60": "-07 58 41.44", "delta": 4.688721695030, "r": 3.715134504989, "elong": 11.68018, "mag": 22.638, "sigPos": 3023.809, "sigPA": 109 }
        }
      }
    }
  }
}