{
  "num": 1,
  "ids":
  [
    "a004042"
  ],
  "objects":
  {
    "a004042":
    {
      "object": "a004042",
      "packed": "a004042",
      "created": 2460945.66007,
      "created iso": "2025-09-27T03:50:29Z",
      "Find_Orb_version": 2460934.50000,
      "Find_Orb_version_iso": "2025-09-16T00:00:00Z",
      "elements":
      {
        "central body": "Sun",
        "frame": "J2000 ecliptic",
        "reference": "Find_Orb",
        "epoch_iso": "2022-08-29T00:00:00Z",
        "epoch":  2459820.50000000,
        "P": 1437.2455559338880, "P sigma": 8.06,
        "M":   7.0715592646233, "M sigma": 1.1,
        "n":   0.2504791185568, "n sigma": 0.00142,
        "a":   2.4924227023184, "a sigma": 0.00933,
        "e":   0.2142681113007, "e sigma": 0.00294,
        "q":   1.9583759973296, "q sigma": 0.0137,
        "Q":   3.0264694073072, "Q sigma": 0.00754,
        "i":   2.3745532012872, "i sigma": 0.014,
        "arg_per":  256.3895684645017, "arg_per sigma":  2.0,
        "asc_node":  71.2305481975356, "asc_node sigma": 0.23,
        "Tp": 2459792.26786909, "Tp sigma": 4.3,
        "Tp_iso": "2022-07-31T18:25:43.889Z",
        "H":  19.27,
        "G":   0.15,
        "rms_residual": 0.17032,
        "weighted_rms_residual": 0.8509,
        "n_resids": 16,
        "U": 8.3669,
        "p_NEO": 0.0000,
        "MOIDs":
        {
          "Mercury" : 1.546109,
          "Venus" : 1.230476,
          "Earth" : 0.948055,
          "Mars" : 0.575047,
          "Jupiter" : 2.309588,
          "Saturn" : 6.124510,
          "Uranus" : 15.287853,
          "Neptune" : 27.049889 
        }
      },
      "observations":
      {
        "count": 9,
        "used": 8,
        "earliest": 2459810.01995300,
        "latest": 2459820.98767900,
        "earliest iso": "2022-08-18T12:28:43.939Z",
        "latest iso": "2022-08-29T11:42:15.465Z",
        "earliest_used": 2459810.01995300,
        "latest_used": 2459820.98767900,
        "earliest_used iso": "2022-08-18T12:28:43.939Z",
        "latest_used iso": "2022-08-29T11:42:15.465Z",
        "earliest_unbanned": 2459810.01995300,
        "latest_unbanned": 2459820.98767900,
        "earliest_unbanned iso": "2022-08-18T12:28:43.939Z",
        "latest_unbanned iso": "2022-08-29T11:42:15.465Z",
        "residuals":
        [
          {"JD": 2459810.019953, "iso date": "2022-08-18T12:28:43.939Z", "obscode": "F51",
                 "RA" : 347.484729, "Dec": -10.507531,
                 "dRA" : 0.0863, "dDec": -0.0467, "dTime": -7.486, "cross": -0.0805,
                 "reference" : "     ",  "packed" : "     a004042",
                 "sigma_1" : 0.200000,
                 "sigma_2" : 0.200000,
                 "normalized_resid_1" : 0.280219,
                 "normalized_resid_2" : 0.402660,
                 "posn_sigma_theta" : 0.000000,
                 "RAMotion" : -0.4015,
                 "decMotion" : -0.2022,
                 "TotalMotion" : 0.4495,
                 "PAMotion" : 243.27, "dMag" : -0.36, "MagObs" : 21.10,
                 "MagBand" : "w", "MagSigma" : 0.5000,
                 "net" : " ",
                 "note1" : " ",
                 "note2" : "C",
                 "discovery_asterisk" : " ",
                 "flags" : 0,
                 "incl" : 1,
                 "ecliptic_lon" : 344.398623,
                 "ecliptic_lat" : -4.735938,
                 "earth_ecliptic_lon" : 326.544021 },
          {"JD": 2459810.031251, "iso date": "2022-08-18T12:45:00.086Z", "obscode": "F51",
                 "RA" : 347.482842, "Dec": -10.508414,
                 "dRA" : -0.086, "dDec": 0.051, "dTime": 7.208, "cross": 0.085,
                 "reference" : "     ",  "packed" : "     a004042",
                 "sigma_1" : 0.200000,
                 "sigma_2" : 0.200000,
                 "normalized_resid_1" : -0.269497,
                 "normalized_resid_2" : -0.423575,
                 "posn_sigma_theta" : 0.000000,
                 "RAMotion" : -0.4011,
                 "decMotion" : -0.2018,
                 "TotalMotion" : 0.4490,
                 "PAMotion" : 243.29, "dMag" : -0.36, "MagObs" : 21.10,
                 "MagBand" : "w", "MagSigma" : 0.5000,
                 "net" : " ",
                 "note1" : " ",
                 "note2" : "C",
                 "discovery_asterisk" : " ",
                 "flags" : 0,
                 "incl" : 1,
                 "ecliptic_lon" : 344.396563,
                 "ecliptic_lat" : -4.736028,
                 "earth_ecliptic_lon" : 326.555156 },
          {"JD": 2459819.910172, "iso date": "2022-08-28T09:50:38.860Z", "obscode": "F52",
                 "RA" : 345.776992, "Dec": -11.346067,
                 "dRA" : -0.327, "dDec": -0.094, "dTime": 36.694, "cross": 0.042,
                 "reference" : "     ",  "packed" : "     a004042",
                 "sigma_1" : 0.200000,
                 "sigma_2" : 0.200000,
                 "normalized_resid_1" : -1.687734,
                 "normalized_resid_2" : -0.212202,
                 "posn_sigma_theta" : 0.000000,
                 "RAMotion" : -0.5081,
                 "decMotion" : -0.2170,
                 "TotalMotion" : 0.5525,
                 "PAMotion" : 246.88, "dMag" : -0.18, "MagObs" : 21.00,
                 "MagBand" : "w", "MagSigma" : 0.5000,
                 "net" : " ",
                 "note1" : " ",
                 "note2" : "C",
                 "discovery_asterisk" : " ",
                 "flags" : 0,
                 "incl" : 1,
                 "ecliptic_lon" : 342.521250,
                 "ecliptic_lat" : -4.857501,
                 "earth_ecliptic_lon" : 336.291911 },
          {"JD": 2459819.937140, "iso date": "2022-08-28T10:29:28.896Z", "obscode": "F52",
                 "RA" : 345.771592, "Dec": -11.348353,
                 "dRA" : 0.332, "dDec": 0.061, "dTime": -35.734, "cross": -0.074,
                 "reference" : "     ",  "packed" : "     a004042",
                 "sigma_1" : 0.200000,
                 "sigma_2" : 0.200000,
                 "normalized_resid_1" : 1.646601,
                 "normalized_resid_2" : 0.368272,
                 "posn_sigma_theta" : 0.000000,
                 "RAMotion" : -0.5098,
                 "decMotion" : -0.2158,
                 "TotalMotion" : 0.5535,
                 "PAMotion" : 247.06, "dMag" : -0.08, "MagObs" : 21.10,
                 "MagBand" : "w", "MagSigma" : 0.5000,
                 "net" : " ",
                 "note1" : " ",
                 "note2" : "C",
                 "discovery_asterisk" : " ",
                 "flags" : 0,
                 "incl" : 1,
                 "ecliptic_lon" : 342.515463,
                 "ecliptic_lat" : -4.857561,
                 "earth_ecliptic_lon" : 336.318490 },
          {"JD": 2459819.950625, "iso date": "2022-08-28T10:48:54.000Z", "obscode": "F52",
                 "RA" : 345.768958, "Dec": -11.349603,
                 "dRA" : 0.917, "dDec": -0.265, "dTime": -80.396, "cross": -0.600,
                 "reference" : "     ",  "packed" : "     a004042",
                 "sigma_1" : 0.200000,
                 "sigma_2" : 0.200000,
                 "normalized_resid_1" : 3.705551,
                 "normalized_resid_2" : 3.002261,
                 "posn_sigma_theta" : 0.000000,
                 "RAMotion" : -0.5102,
                 "decMotion" : -0.2151,
                 "TotalMotion" : 0.5537,
                 "PAMotion" : 247.14, "dMag" : -0.28, "MagObs" : 20.90,
                 "MagBand" : "w", "MagSigma" : 0.5000,
                 "net" : " ",
                 "note1" : " ",
                 "note2" : "C",
                 "discovery_asterisk" : " ",
                 "flags" : 0,
                 "incl" : 0,
                 "ecliptic_lon" : 342.512588,
                 "ecliptic_lat" : -4.857714,
                 "earth_ecliptic_lon" : 336.331781 },
          {"JD": 2459820.954464, "iso date": "2022-08-29T10:54:25.689Z", "obscode": "F51",
                 "RA" : 345.574075, "Dec": -11.435325,
                 "dRA" : -0.340, "dDec": -0.001, "dTime": 33.759, "cross": 0.129,
                 "reference" : "     ",  "packed" : "     a004042",
                 "sigma_1" : 0.200000,
                 "sigma_2" : 0.200000,
                 "normalized_resid_1" : -1.570458,
                 "normalized_resid_2" : -0.644538,
                 "posn_sigma_theta" : 0.000000,
                 "RAMotion" : -0.5164,
                 "decMotion" : -0.2136,
                 "TotalMotion" : 0.5588,
                 "PAMotion" : 247.53, "dMag" : 0.55, "MagObs" : 21.70,
                 "MagBand" : "w", "MagSigma" : 0.5000,
                 "net" : " ",
                 "note1" : " ",
                 "note2" : "C",
                 "discovery_asterisk" : " ",
                 "flags" : 0,
                 "incl" : 1,
                 "ecliptic_lon" : 342.302502,
                 "ecliptic_lat" : -4.862870,
                 "earth_ecliptic_lon" : 337.321174 },
          {"JD": 2459820.965511, "iso date": "2022-08-29T11:10:20.150Z", "obscode": "F51",
                 "RA" : 345.571850, "Dec": -11.436214,
                 "dRA" : 0.005, "dDec": 0.185, "dTime": -8.059, "cross": 0.169,
                 "reference" : "     ",  "packed" : "     a004042",
                 "sigma_1" : 0.200000,
                 "sigma_2" : 0.200000,
                 "normalized_resid_1" : 0.374800,
                 "normalized_resid_2" : -0.845653,
                 "posn_sigma_theta" : 0.000000,
                 "RAMotion" : -0.5164,
                 "decMotion" : -0.2131,
                 "TotalMotion" : 0.5587,
                 "PAMotion" : 247.58, "dMag" : 0.35, "MagObs" : 21.50,
                 "MagBand" : "w", "MagSigma" : 0.5000,
                 "net" : " ",
                 "note1" : " ",
                 "note2" : "C",
                 "discovery_asterisk" : " ",
                 "flags" : 0,
                 "incl" : 1,
                 "ecliptic_lon" : 342.300139,
                 "ecliptic_lat" : -4.862846,
                 "earth_ecliptic_lon" : 337.332062 },
          {"JD": 2459820.976562, "iso date": "2022-08-29T11:26:14.956Z", "obscode": "F51",
                 "RA" : 345.569529, "Dec": -11.437214,
                 "dRA" : 0.0131, "dDec": -0.0362, "dTime": 0.174, "cross": -0.0385,
                 "reference" : "     ",  "packed" : "     a004042",
                 "sigma_1" : 0.200000,
                 "sigma_2" : 0.200000,
                 "normalized_resid_1" : -0.008077,
                 "normalized_resid_2" : 0.192320,
                 "posn_sigma_theta" : 0.000000,
                 "RAMotion" : -0.5163,
                 "decMotion" : -0.2125,
                 "TotalMotion" : 0.5583,
                 "PAMotion" : 247.62, "dMag" : 0.25, "MagObs" : 21.40,
                 "MagBand" : "w", "MagSigma" : 0.5000,
                 "net" : " ",
                 "note1" : " ",
                 "note2" : "C",
                 "discovery_asterisk" : " ",
                 "flags" : 0,
                 "incl" : 1,
                 "ecliptic_lon" : 342.297645,
                 "ecliptic_lat" : -4.862889,
                 "earth_ecliptic_lon" : 337.342954 },
          {"JD": 2459820.987679, "iso date": "2022-08-29T11:42:15.465Z", "obscode": "F51",
                 "RA" : 345.567254, "Dec": -11.438175,
                 "dRA" : 0.228, "dDec": -0.106, "dTime": -18.364, "cross": -0.184,
                 "reference" : "     ",  "packed" : "     a004042",
                 "sigma_1" : 0.200000,
                 "sigma_2" : 0.200000,
                 "normalized_resid_1" : 0.852634,
                 "normalized_resid_2" : 0.921510,
                 "posn_sigma_theta" : 0.000000,
                 "RAMotion" : -0.5159,
                 "decMotion" : -0.2120,
                 "TotalMotion" : 0.5578,
                 "PAMotion" : 247.66, "dMag" : -0.15, "MagObs" : 21.00,
                 "MagBand" : "w", "MagSigma" : 0.5000,
                 "net" : " ",
                 "note1" : " ",
                 "note2" : "C",
                 "discovery_asterisk" : " ",
                 "flags" : 0,
                 "incl" : 1,
                 "ecliptic_lon" : 342.295208,
                 "ecliptic_lat" : -4.862913,
                 "earth_ecliptic_lon" : 337.353911 } 
        ]
      },
      "ephemeris":
      {
        "obscode": "500",
        "packed": "a004042",
        "count": 10,
        "start": 2460945.500000,
        "step": 1.000000000,
        "n_steps": 10,
        "start iso": "2025-09-27T00:00:00.000Z",
        "entries":
        {
          "0": {"JD": 2460945.500000000, "ISO_time": "2025-09-27T00:00:00Z", "RA": 216.15893117968, "RA60": "14 24 38.143", "Dec": -13.71466713860, "Dec60": "-13 42 52.80", "delta": 3.188699373207, "r": 2.430391731257, "elong": 34.54209, "mag": 24.497, "sigPos": 946.908, "sigPA": 112 },
          "1": {"JD": 2460946.500000000, "ISO_time": "2025-09-28T00:00:00Z", "RA": 216.58343596089, "RA60": "14 26 20.025", "Dec": -13.86366071125, "Dec60": "-13 51 49.18", "delta": 3.193277032137, "r": 2.428013267012, "elong": 33.99916, "mag": 24.492, "sigPos": 966.891, "sigPA": 112 },
          "2": {"JD": 2460947.500000000, "ISO_time": "2025-09-29T00:00:00Z", "RA": 217.00996315670, "RA60": "14 28 02.391", "Dec": -14.01232811482, "Dec60": "-14 00 44.38", "delta": 3.197747896801, "r": 2.425633767002, "elong": 33.45723, "mag": 24.486, "sigPos": 986.968, "sigPA": 112 },
          "3": {"JD": 2460948.500000000, "ISO_time": "2025-09-30T00:00:00Z", "RA": 217.43850333928, "RA60": "14 29 45.241", "Dec": -14.16064755896, "Dec60": "-14 09 38.33", "delta": 3.202111852695, "r": 2.423253277513, "elong": 32.91628, "mag": 24.480, "sigPos": 1007.138, "sigPA": 112 },
          "4": {"JD": 2460949.500000000, "ISO_time": "2025-10-01T00:00:00Z", "RA": 217.86904759167, "RA60": "14 31 28.571", "Dec": -14.30859748863, "Dec60": "-14 18 30.95", "delta": 3.206368839470, "r": 2.420871845127, "elong": 32.37630, "mag": 24.474, "sigPos": 1027.403, "sigPA": 111 },
          "5": {"JD": 2460950.500000000, "ISO_time": "2025-10-02T00:00:00Z", "RA": 218.30158762952, "RA60": "14 33 12.381", "Dec": -14.45615663082, "Dec60": "-14 27 22.16", "delta": 3.210518851963, "r": 2.418489516731, "elong": 31.83727, "mag": 24.468, "sigPos": 1047.763, "sigPA": 111 },
          "6": {"JD": 2460951.500000000, "ISO_time": "2025-10-03T00:00:00Z", "RA": 218.73611598644, "RA60": "14 34 56.668", "Dec": -14.60330406084, "Dec60": "-14 36 11.89", "delta": 3.214561940164, "r": 2.416106339508, "elong": 31.29917, "mag": 24.462, "sigPos": 1068.218, "sigPA": 111 },
          "7": {"JD": 2460952.500000000, "ISO_time": "2025-10-04T00:00:00Z", "RA": 219.17262626991, "RA60": "14 36 41.430", "Dec": -14.75001928524, "Dec60": "-14 45 00.07", "delta": 3.218498205517, "r": 2.413722360948, "elong": 30.76198, "mag": 24.455, "sigPos": 1088.768, "sigPA": 111 },
          "8": {"JD": 2460953.500000000, "ISO_time": "2025-10-05T00:00:00Z", "RA": 219.61111346843, "RA60": "14 38 26.667", "Dec": -14.89628232738, "Dec60": "-14 53 46.62", "delta": 3.222327790348, "r": 2.411337628841, "elong": 30.22567, "mag": 24.449, "sigPos": 1109.414, "sigPA": 111 },
          "9": {"JD": 2460954.500000000, "ISO_time": "2025-10-06T00:00:00Z", "RA": 220.05157424985, "RA60": "14 40 12.378", "Dec": -15.04207378770, "Dec60": "-15 02 31.47", "delta": 3.226050857504, "r": 2.408952191284, "elong": 29.69022, "mag": 24.442, "sigPos": 1130.156, "sigPA": 111 }
        }
      }
    }
  }
}