{
  "num": 1,
  "ids":
  [
    "a000218"
  ],
  "objects":
  {
    "a000218":
    {
      "object": "a000218",
      "packed": "a000218",
      "created": 2460945.65082,
      "created iso": "2025-09-27T03:37:10Z",
      "Find_Orb_version": 2460934.50000,
      "Find_Orb_version_iso": "2025-09-16T00:00:00Z",
      "elements":
      {
        "central body": "Sun",
        "frame": "J2000 ecliptic",
        "reference": "Find_Orb",
        "epoch_iso": "2022-08-30T00:00:00Z",
        "epoch":  2459821.50000000,
        "P": 2085.4354353691929, "P sigma": 6.87,
        "M":  33.0199947263344, "M sigma": 17,
        "n":   0.1726258189989, "n sigma": 0.000569,
        "a":   3.1944704950978, "a sigma": 0.00702,
        "e":   0.0554231763402, "e sigma": 0.0142,
        "q":   3.0174227935345, "q sigma": 0.0387,
        "Q":   3.3715181966610, "Q sigma": 0.0528,
        "i":   4.9893040979699, "i sigma": 0.25,
        "arg_per":  141.6550282345625, "arg_per sigma":  18,
        "asc_node": 151.7605761323701, "asc_node sigma": 0.13,
        "Tp": 2459630.21925812, "Tp sigma": 103,
        "Tp_iso": "2022-02-19T17:15:43.901Z",
        "H":  15.80,
        "G":   0.15,
        "rms_residual": 0.10543,
        "weighted_rms_residual": 0.5269,
        "n_resids": 22,
        "U": 7.9841,
        "p_NEO": 0.0000,
        "MOIDs":
        {
          "Mercury" : 2.569547,
          "Venus" : 2.293240,
          "Earth" : 2.003213,
          "Mars" : 1.564368,
          "Jupiter" : 1.747743,
          "Saturn" : 5.670343,
          "Uranus" : 14.984093,
          "Neptune" : 26.520825 
        }
      },
      "observations":
      {
        "count": 11,
        "used": 11,
        "earliest": 2459809.93382900,
        "latest": 2459821.88881100,
        "earliest iso": "2022-08-18T10:24:42.825Z",
        "latest iso": "2022-08-30T09:19:53.270Z",
        "earliest_used": 2459809.93382900,
        "latest_used": 2459821.88881100,
        "earliest_used iso": "2022-08-18T10:24:42.825Z",
        "latest_used iso": "2022-08-30T09:19:53.270Z",
        "earliest_unbanned": 2459809.93382900,
        "latest_unbanned": 2459821.88881100,
        "earliest_unbanned iso": "2022-08-18T10:24:42.825Z",
        "latest_unbanned iso": "2022-08-30T09:19:53.270Z",
        "residuals":
        [
          {"JD": 2459809.933829, "iso date": "2022-08-18T10:24:42.825Z", "obscode": "F51",
                 "RA" : 331.244846, "Dec": -11.248825,
                 "dRA" : 0.0397, "dDec": 0.0058, "dTime": -4.497, "cross": -0.0126,
                 "reference" : "     ",  "packed" : "     a000218",
                 "sigma_1" : 0.200000,
                 "sigma_2" : 0.200000,
                 "normalized_resid_1" : 0.190146,
                 "normalized_resid_2" : 0.062959,
                 "posn_sigma_theta" : 0.000000,
                 "RAMotion" : -0.4539,
                 "decMotion" : -0.2277,
                 "TotalMotion" : 0.5078,
                 "PAMotion" : 243.36, "dMag" : 0.22, "MagObs" : 20.30,
                 "MagBand" : "w", "MagSigma" : 0.5000,
                 "net" : " ",
                 "note1" : " ",
                 "note2" : "C",
                 "discovery_asterisk" : " ",
                 "flags" : 0,
                 "incl" : 1,
                 "ecliptic_lon" : 329.302480,
                 "ecliptic_lat" : 0.498948,
                 "earth_ecliptic_lon" : 326.459136 },
          {"JD": 2459809.946285, "iso date": "2022-08-18T10:42:39.024Z", "obscode": "F51",
                 "RA" : 331.242525, "Dec": -11.249964,
                 "dRA" : -0.0224, "dDec": -0.0155, "dTime": 3.188, "cross": -0.0038,
                 "reference" : "     ",  "packed" : "     a000218",
                 "sigma_1" : 0.200000,
                 "sigma_2" : 0.200000,
                 "normalized_resid_1" : -0.134760,
                 "normalized_resid_2" : 0.019148,
                 "posn_sigma_theta" : 0.000000,
                 "RAMotion" : -0.4540,
                 "decMotion" : -0.2275,
                 "TotalMotion" : 0.5078,
                 "PAMotion" : 243.39, "dMag" : 0.12, "MagObs" : 20.20,
                 "MagBand" : "w", "MagSigma" : 0.5000,
                 "net" : " ",
                 "note1" : " ",
                 "note2" : "C",
                 "discovery_asterisk" : " ",
                 "flags" : 0,
                 "incl" : 1,
                 "ecliptic_lon" : 329.299949,
                 "ecliptic_lat" : 0.498675,
                 "earth_ecliptic_lon" : 326.471413 },
          {"JD": 2459809.958785, "iso date": "2022-08-18T11:00:39.024Z", "obscode": "F51",
                 "RA" : 331.240217, "Dec": -11.251103,
                 "dRA" : -0.0110, "dDec": -0.0271, "dTime": 2.603, "cross": -0.0193,
                 "reference" : "     ",  "packed" : "     a000218",
                 "sigma_1" : 0.200000,
                 "sigma_2" : 0.200000,
                 "normalized_resid_1" : -0.110018,
                 "normalized_resid_2" : 0.096663,
                 "posn_sigma_theta" : 0.000000,
                 "RAMotion" : -0.4539,
                 "decMotion" : -0.2272,
                 "TotalMotion" : 0.5076,
                 "PAMotion" : 243.41, "dMag" : -0.08, "MagObs" : 20.00,
                 "MagBand" : "w", "MagSigma" : 0.5000,
                 "net" : " ",
                 "note1" : " ",
                 "note2" : "C",
                 "discovery_asterisk" : " ",
                 "flags" : 0,
                 "incl" : 1,
                 "ecliptic_lon" : 329.297430,
                 "ecliptic_lat" : 0.498397,
                 "earth_ecliptic_lon" : 326.483733 },
          {"JD": 2459809.971270, "iso date": "2022-08-18T11:18:37.728Z", "obscode": "F51",
                 "RA" : 331.237917, "Dec": -11.252231,
                 "dRA" : 0.0185, "dDec": -0.0084, "dTime": -1.517, "cross": -0.0158,
                 "reference" : "     ",  "packed" : "     a000218",
                 "sigma_1" : 0.200000,
                 "sigma_2" : 0.200000,
                 "normalized_resid_1" : 0.064105,
                 "normalized_resid_2" : 0.079030,
                 "posn_sigma_theta" : 0.000000,
                 "RAMotion" : -0.4538,
                 "decMotion" : -0.2269,
                 "TotalMotion" : 0.5074,
                 "PAMotion" : 243.43, "dMag" : -0.08, "MagObs" : 20.00,
                 "MagBand" : "w", "MagSigma" : 0.5000,
                 "net" : " ",
                 "note1" : " ",
                 "note2" : "C",
                 "discovery_asterisk" : " ",
                 "flags" : 0,
                 "incl" : 1,
                 "ecliptic_lon" : 329.294923,
                 "ecliptic_lat" : 0.498126,
                 "earth_ecliptic_lon" : 326.496038 },
          {"JD": 2459813.912865, "iso date": "2022-08-22T09:54:31.536Z", "obscode": "F51",
                 "RA" : 330.533867, "Dec": -11.611303,
                 "dRA" : -0.237, "dDec": 0.145, "dTime": 17.311, "cross": 0.235,
                 "reference" : "     ",  "packed" : "     a000218",
                 "sigma_1" : 0.200000,
                 "sigma_2" : 0.200000,
                 "normalized_resid_1" : -0.736010,
                 "normalized_resid_2" : -1.176634,
                 "posn_sigma_theta" : 0.000000,
                 "RAMotion" : -0.4567,
                 "decMotion" : -0.2284,
                 "TotalMotion" : 0.5107,
                 "PAMotion" : 243.43, "dMag" : 0.05, "MagObs" : 20.00,
                 "MagBand" : "w", "MagSigma" : 0.5000,
                 "net" : " ",
                 "note1" : " ",
                 "note2" : "C",
                 "discovery_asterisk" : " ",
                 "flags" : 0,
                 "incl" : 1,
                 "ecliptic_lon" : 328.523043,
                 "ecliptic_lat" : 0.401258,
                 "earth_ecliptic_lon" : 330.380910 },
          {"JD": 2459813.937841, "iso date": "2022-08-22T10:30:29.462Z", "obscode": "F51",
                 "RA" : 330.529242, "Dec": -11.613608,
                 "dRA" : -0.135, "dDec": 0.041, "dTime": 11.999, "cross": 0.097,
                 "reference" : "     ",  "packed" : "     a000218",
                 "sigma_1" : 0.200000,
                 "sigma_2" : 0.200000,
                 "normalized_resid_1" : -0.510030,
                 "normalized_resid_2" : -0.483780,
                 "posn_sigma_theta" : 0.000000,
                 "RAMotion" : -0.4569,
                 "decMotion" : -0.2278,
                 "TotalMotion" : 0.5105,
                 "PAMotion" : 243.50, "dMag" : 0.15, "MagObs" : 20.10,
                 "MagBand" : "w", "MagSigma" : 0.5000,
                 "net" : " ",
                 "note1" : " ",
                 "note2" : "C",
                 "discovery_asterisk" : " ",
                 "flags" : 0,
                 "incl" : 1,
                 "ecliptic_lon" : 328.517994,
                 "ecliptic_lat" : 0.400664,
                 "earth_ecliptic_lon" : 330.405527 },
          {"JD": 2459813.950303, "iso date": "2022-08-22T10:48:26.179Z", "obscode": "F51",
                 "RA" : 330.527054, "Dec": -11.614789,
                 "dRA" : 0.341, "dDec": -0.127, "dTime": -29.186, "cross": -0.265,
                 "reference" : "     ",  "packed" : "     a000218",
                 "sigma_1" : 0.200000,
                 "sigma_2" : 0.200000,
                 "normalized_resid_1" : 1.240095,
                 "normalized_resid_2" : 1.326836,
                 "posn_sigma_theta" : 0.000000,
                 "RAMotion" : -0.4568,
                 "decMotion" : -0.2275,
                 "TotalMotion" : 0.5103,
                 "PAMotion" : 243.52, "dMag" : -0.15, "MagObs" : 19.80,
                 "MagBand" : "w", "MagSigma" : 0.5000,
                 "net" : " ",
                 "note1" : " ",
                 "note2" : "C",
                 "discovery_asterisk" : " ",
                 "flags" : 0,
                 "incl" : 1,
                 "ecliptic_lon" : 328.515575,
                 "ecliptic_lat" : 0.400298,
                 "earth_ecliptic_lon" : 330.417809 },
          {"JD": 2459821.852349, "iso date": "2022-08-30T08:27:22.953Z", "obscode": "F52",
                 "RA" : 329.130496, "Dec": -12.323597,
                 "dRA" : 0.00735, "dDec": -0.00458, "dTime": -0.552, "cross": -0.00739,
                 "reference" : "     ",  "packed" : "     a000218",
                 "sigma_1" : 0.200000,
                 "sigma_2" : 0.200000,
                 "normalized_resid_1" : 0.022534,
                 "normalized_resid_2" : 0.036954,
                 "posn_sigma_theta" : 0.000000,
                 "RAMotion" : -0.4378,
                 "decMotion" : -0.2201,
                 "TotalMotion" : 0.4901,
                 "PAMotion" : 243.31, "dMag" : -0.13, "MagObs" : 20.10,
                 "MagBand" : "w", "MagSigma" : 0.5000,
                 "net" : " ",
                 "note1" : " ",
                 "note2" : "C",
                 "discovery_asterisk" : " ",
                 "flags" : 0,
                 "incl" : 1,
                 "ecliptic_lon" : 326.988941,
                 "ecliptic_lat" : 0.204534,
                 "earth_ecliptic_lon" : 338.206138 },
          {"JD": 2459821.864484, "iso date": "2022-08-30T08:44:51.417Z", "obscode": "F52",
                 "RA" : 329.128300, "Dec": -12.324658,
                 "dRA" : -0.0701, "dDec": 0.0158, "dTime": 6.798, "cross": 0.0455,
                 "reference" : "     ",  "packed" : "     a000218",
                 "sigma_1" : 0.200000,
                 "sigma_2" : 0.200000,
                 "normalized_resid_1" : -0.277505,
                 "normalized_resid_2" : -0.227749,
                 "posn_sigma_theta" : 0.000000,
                 "RAMotion" : -0.4382,
                 "decMotion" : -0.2198,
                 "TotalMotion" : 0.4902,
                 "PAMotion" : 243.36, "dMag" : -0.13, "MagObs" : 20.10,
                 "MagBand" : "w", "MagSigma" : 0.5000,
                 "net" : " ",
                 "note1" : " ",
                 "note2" : "C",
                 "discovery_asterisk" : " ",
                 "flags" : 0,
                 "incl" : 1,
                 "ecliptic_lon" : 326.986562,
                 "ecliptic_lat" : 0.204269,
                 "earth_ecliptic_lon" : 338.218098 },
          {"JD": 2459821.876609, "iso date": "2022-08-30T09:02:19.017Z", "obscode": "F52",
                 "RA" : 329.126150, "Dec": -12.325722,
                 "dRA" : 0.0130, "dDec": 0.0178, "dTime": -2.396, "cross": 0.0101,
                 "reference" : "     ",  "packed" : "     a000218",
                 "sigma_1" : 0.200000,
                 "sigma_2" : 0.200000,
                 "normalized_resid_1" : 0.097835,
                 "normalized_resid_2" : -0.050716,
                 "posn_sigma_theta" : 0.000000,
                 "RAMotion" : -0.4385,
                 "decMotion" : -0.2195,
                 "TotalMotion" : 0.4904,
                 "PAMotion" : 243.41, "dMag" : -0.13, "MagObs" : 20.10,
                 "MagBand" : "w", "MagSigma" : 0.5000,
                 "net" : " ",
                 "note1" : " ",
                 "note2" : "C",
                 "discovery_asterisk" : " ",
                 "flags" : 0,
                 "incl" : 1,
                 "ecliptic_lon" : 326.984224,
                 "ecliptic_lat" : 0.203986,
                 "earth_ecliptic_lon" : 338.230049 },
          {"JD": 2459821.888811, "iso date": "2022-08-30T09:19:53.270Z", "obscode": "F52",
                 "RA" : 329.123975, "Dec": -12.326811,
                 "dRA" : 0.0605, "dDec": -0.0511, "dTime": -3.825, "cross": -0.0728,
                 "reference" : "     ",  "packed" : "     a000218",
                 "sigma_1" : 0.200000,
                 "sigma_2" : 0.200000,
                 "normalized_resid_1" : 0.156153,
                 "normalized_resid_2" : 0.363919,
                 "posn_sigma_theta" : 0.000000,
                 "RAMotion" : -0.4386,
                 "decMotion" : -0.2192,
                 "TotalMotion" : 0.4904,
                 "PAMotion" : 243.45, "dMag" : 0.17, "MagObs" : 20.40,
                 "MagBand" : "w", "MagSigma" : 0.5000,
                 "net" : " ",
                 "note1" : " ",
                 "note2" : "C",
                 "discovery_asterisk" : " ",
                 "flags" : 0,
                 "incl" : 1,
                 "ecliptic_lon" : 326.981855,
                 "ecliptic_lat" : 0.203688,
                 "earth_ecliptic_lon" : 338.242075 } 
        ]
      },
      "ephemeris":
      {
        "obscode": "500",
        "packed": "a000218",
        "count": 10,
        "start": 2460945.500000,
        "step": 1.000000000,
        "n_steps": 10,
        "start iso": "2025-09-27T00:00:00.000Z",
        "entries":
        {
          "0": {"JD": 2460945.500000000, "ISO_time": "2025-09-27T00:00:00Z", "RA": 163.84072963980, "RA60": "10 55 21.775", "Dec": 7.19517665851, "Dec60": "+07 11 42.64", "delta": 4.232757660117, "r": 3.320031657494, "elong": 21.44586, "mag": 22.028, "sigPos": 602.499, "sigPA": 111 },
          "1": {"JD": 2460946.500000000, "ISO_time": "2025-09-28T00:00:00Z", "RA": 164.16078343118, "RA60": "10 56 38.588", "Dec": 7.07594427561, "Dec60": "+07 04 33.40", "delta": 4.226795439060, "r": 3.319669378153, "elong": 22.08808, "mag": 22.033, "sigPos": 567.763, "sigPA": 111 },
          "2": {"JD": 2460947.500000000, "ISO_time": "2025-09-29T00:00:00Z", "RA": 164.48021524123, "RA60": "10 57 55.252", "Dec": 6.95673896283, "Dec60": "+06 57 24.26", "delta": 4.220681451114, "r": 3.319306006186, "elong": 22.73131, "mag": 22.039, "sigPos": 532.996, "sigPA": 112 },
          "3": {"JD": 2460948.500000000, "ISO_time": "2025-09-30T00:00:00Z", "RA": 164.79901142693, "RA60": "10 59 11.763", "Dec": 6.83757427004, "Dec60": "+06 50 15.27", "delta": 4.214416440767, "r": 3.318941544174, "elong": 23.37555, "mag": 22.043, "sigPos": 498.203, "sigPA": 112 },
          "4": {"JD": 2460949.500000000, "ISO_time": "2025-10-01T00:00:00Z", "RA": 165.11715880238, "RA60": "11 00 28.118", "Dec": 6.71846349950, "Dec60": "+06 43 06.47", "delta": 4.208001173050, "r": 3.318575994707, "elong": 24.02082, "mag": 22.048, "sigPos": 463.385, "sigPA": 113 },
          "5": {"JD": 2460950.500000000, "ISO_time": "2025-10-02T00:00:00Z", "RA": 165.43464470012, "RA60": "11 01 44.315", "Dec": 6.59941966769, "Dec60": "+06 35 57.91", "delta": 4.201436427403, "r": 3.318209360385, "elong": 24.66715, "mag": 22.053, "sigPos": 428.551, "sigPA": 113 },
          "6": {"JD": 2460951.500000000, "ISO_time": "2025-10-03T00:00:00Z", "RA": 165.75145704600, "RA60": "11 03 00.350", "Dec": 6.48045546031, "Dec60": "+06 28 49.64", "delta": 4.194722987830, "r": 3.317841643816, "elong": 25.31454, "mag": 22.057, "sigPos": 393.708, "sigPA": 114 },
          "7": {"JD": 2460952.500000000, "ISO_time": "2025-10-04T00:00:00Z", "RA": 166.06758442310, "RA60": "11 04 16.220", "Dec": 6.36158319378, "Dec60": "+06 21 41.70", "delta": 4.187861627645, "r": 3.317472847619, "elong": 25.96304, "mag": 22.061, "sigPos": 358.869, "sigPA": 115 },
          "8": {"JD": 2460953.500000000, "ISO_time": "2025-10-05T00:00:00Z", "RA": 166.38301608240, "RA60": "11 05 31.924", "Dec": 6.24281480602, "Dec60": "+06 14 34.13", "delta": 4.180853088094, "r": 3.317102974423, "elong": 26.61265, "mag": 22.065, "sigPos": 324.052, "sigPA": 116 },
          "9": {"JD": 2460954.500000000, "ISO_time": "2025-10-06T00:00:00Z", "RA": 166.69774184530, "RA60": "11 06 47.458", "Dec": 6.12416190643, "Dec60": "+06 07 26.98", "delta": 4.173698052319, "r": 3.316732026865, "elong": 27.26342, "mag": 22.069, "sigPos": 289.286, "sigPA": 117 }
        }
      }
    }
  }
}