{
  "num": 1,
  "ids":
  [
    "a001512"
  ],
  "objects":
  {
    "a001512":
    {
      "object": "a001512",
      "packed": "a001512",
      "created": 2460945.65382,
      "created iso": "2025-09-27T03:41:30Z",
      "Find_Orb_version": 2460934.50000,
      "Find_Orb_version_iso": "2025-09-16T00:00:00Z",
      "elements":
      {
        "central body": "Sun",
        "frame": "J2000 ecliptic",
        "reference": "Find_Orb",
        "epoch_iso": "2022-08-30T00:00:00Z",
        "epoch":  2459821.50000000,
        "P": 1959.0857249839289, "P sigma": 7.1,
        "M": 305.6148140628582, "M sigma": 11,
        "n":   0.1837591869559, "n sigma": 0.000666,
        "a":   3.0641028738764, "a sigma": 0.0074,
        "e":   0.1092490023841, "e sigma": 0.0187,
        "q":   2.7293526917033, "q sigma": 0.0507,
        "Q":   3.3988530560496, "Q sigma": 0.0654,
        "i":   8.9368192004712, "i sigma": 0.58,
        "arg_per":   72.0426730384405, "arg_per sigma":  9,
        "asc_node": 322.2843633810633, "asc_node sigma": 0.24,
        "Tp": 2460117.45900394, "Tp sigma": 59.2,
        "Tp_iso": "2023-06-21T23:00:57.940Z",
        "H":  16.38,
        "G":   0.15,
        "rms_residual": 0.03236,
        "weighted_rms_residual": 0.1617,
        "n_resids": 20,
        "U": 8.0965,
        "p_NEO": 0.0000,
        "MOIDs":
        {
          "Mercury" : 2.407182,
          "Venus" : 2.022690,
          "Earth" : 1.751131,
          "Mars" : 1.287549,
          "Jupiter" : 2.074910,
          "Saturn" : 6.044437,
          "Uranus" : 14.983563,
          "Neptune" : 26.940257 
        }
      },
      "observations":
      {
        "count": 10,
        "used": 10,
        "earliest": 2459809.93173800,
        "latest": 2459821.88944200,
        "earliest iso": "2022-08-18T10:21:42.163Z",
        "latest iso": "2022-08-30T09:20:47.788Z",
        "earliest_used": 2459809.93173800,
        "latest_used": 2459821.88944200,
        "earliest_used iso": "2022-08-18T10:21:42.163Z",
        "latest_used iso": "2022-08-30T09:20:47.788Z",
        "earliest_unbanned": 2459809.93173800,
        "latest_unbanned": 2459821.88944200,
        "earliest_unbanned iso": "2022-08-18T10:21:42.163Z",
        "latest_unbanned iso": "2022-08-30T09:20:47.788Z",
        "residuals":
        [
          {"JD": 2459809.931738, "iso date": "2022-08-18T10:21:42.163Z", "obscode": "F51",
                 "RA" : 329.127675, "Dec": -11.451150,
                 "dRA" : 0.0234, "dDec": 0.0283, "dTime": -2.894, "cross": 0.0255,
                 "reference" : "     ",  "packed" : "     a001512",
                 "sigma_1" : 0.200000,
                 "sigma_2" : 0.200000,
                 "normalized_resid_1" : 0.131936,
                 "normalized_resid_2" : -0.127280,
                 "posn_sigma_theta" : 0.000000,
                 "RAMotion" : -0.5441,
                 "decMotion" : -0.0617,
                 "TotalMotion" : 0.5476,
                 "PAMotion" : 263.53, "dMag" : 0.05, "MagObs" : 20.40,
                 "MagBand" : "w", "MagSigma" : 0.5000,
                 "net" : " ",
                 "note1" : " ",
                 "note2" : "C",
                 "discovery_asterisk" : " ",
                 "flags" : 0,
                 "incl" : 1,
                 "ecliptic_lon" : 327.284258,
                 "ecliptic_lat" : 1.025491,
                 "earth_ecliptic_lon" : 326.457075 },
          {"JD": 2459809.944213, "iso date": "2022-08-18T10:39:40.003Z", "obscode": "F51",
                 "RA" : 329.124896, "Dec": -11.451475,
                 "dRA" : -0.0174, "dDec": -0.0397, "dTime": 2.383, "cross": -0.0375,
                 "reference" : "     ",  "packed" : "     a001512",
                 "sigma_1" : 0.200000,
                 "sigma_2" : 0.200000,
                 "normalized_resid_1" : -0.108626,
                 "normalized_resid_2" : 0.187282,
                 "posn_sigma_theta" : 0.000000,
                 "RAMotion" : -0.5442,
                 "decMotion" : -0.0614,
                 "TotalMotion" : 0.5476,
                 "PAMotion" : 263.56, "dMag" : 0.05, "MagObs" : 20.40,
                 "MagBand" : "w", "MagSigma" : 0.5000,
                 "net" : " ",
                 "note1" : " ",
                 "note2" : "C",
                 "discovery_asterisk" : " ",
                 "flags" : 0,
                 "incl" : 1,
                 "ecliptic_lon" : 327.281587,
                 "ecliptic_lat" : 1.026116,
                 "earth_ecliptic_lon" : 326.469371 },
          {"JD": 2459809.956684, "iso date": "2022-08-18T10:57:37.497Z", "obscode": "F51",
                 "RA" : 329.122129, "Dec": -11.451769,
                 "dRA" : -0.0174, "dDec": -0.0031, "dTime": 1.929, "cross": -0.0012,
                 "reference" : "     ",  "packed" : "     a001512",
                 "sigma_1" : 0.200000,
                 "sigma_2" : 0.200000,
                 "normalized_resid_1" : -0.087916,
                 "normalized_resid_2" : 0.005921,
                 "posn_sigma_theta" : 0.000000,
                 "RAMotion" : -0.5441,
                 "decMotion" : -0.0611,
                 "TotalMotion" : 0.5475,
                 "PAMotion" : 263.59, "dMag" : 0.05, "MagObs" : 20.40,
                 "MagBand" : "w", "MagSigma" : 0.5000,
                 "net" : " ",
                 "note1" : " ",
                 "note2" : "C",
                 "discovery_asterisk" : " ",
                 "flags" : 0,
                 "incl" : 1,
                 "ecliptic_lon" : 327.278937,
                 "ecliptic_lat" : 1.026765,
                 "earth_ecliptic_lon" : 326.481662 },
          {"JD": 2459809.969175, "iso date": "2022-08-18T11:15:36.720Z", "obscode": "F51",
                 "RA" : 329.119367, "Dec": -11.452067,
                 "dRA" : 0.0108, "dDec": 0.0199, "dTime": -1.420, "cross": 0.0186,
                 "reference" : "     ",  "packed" : "     a001512",
                 "sigma_1" : 0.200000,
                 "sigma_2" : 0.200000,
                 "normalized_resid_1" : 0.064690,
                 "normalized_resid_2" : -0.093118,
                 "posn_sigma_theta" : 0.000000,
                 "RAMotion" : -0.5439,
                 "decMotion" : -0.0608,
                 "TotalMotion" : 0.5473,
                 "PAMotion" : 263.62, "dMag" : 0.05, "MagObs" : 20.40,
                 "MagBand" : "w", "MagSigma" : 0.5000,
                 "net" : " ",
                 "note1" : " ",
                 "note2" : "C",
                 "discovery_asterisk" : " ",
                 "flags" : 0,
                 "incl" : 1,
                 "ecliptic_lon" : 327.276290,
                 "ecliptic_lat" : 1.027410,
                 "earth_ecliptic_lon" : 326.493973 },
          {"JD": 2459813.925368, "iso date": "2022-08-22T10:12:31.795Z", "obscode": "F51",
                 "RA" : 328.270096, "Dec": -11.549567,
                 "dRA" : -0.0169, "dDec": -0.0398, "dTime": 2.319, "cross": -0.0376,
                 "reference" : "     ",  "packed" : "     a001512",
                 "sigma_1" : 0.200000,
                 "sigma_2" : 0.200000,
                 "normalized_resid_1" : -0.106011,
                 "normalized_resid_2" : 0.188116,
                 "posn_sigma_theta" : 0.000000,
                 "RAMotion" : -0.5456,
                 "decMotion" : -0.0618,
                 "TotalMotion" : 0.5491,
                 "PAMotion" : 263.54, "dMag" : -0.06, "MagObs" : 20.30,
                 "MagBand" : "w", "MagSigma" : 0.5000,
                 "net" : " ",
                 "note1" : " ",
                 "note2" : "C",
                 "discovery_asterisk" : " ",
                 "flags" : 0,
                 "incl" : 1,
                 "ecliptic_lon" : 326.460329,
                 "ecliptic_lat" : 1.218610,
                 "earth_ecliptic_lon" : 330.393233 },
          {"JD": 2459813.937841, "iso date": "2022-08-22T10:30:29.462Z", "obscode": "F51",
                 "RA" : 328.267337, "Dec": -11.549856,
                 "dRA" : 0.0429, "dDec": 0.0231, "dTime": -4.940, "cross": 0.0182,
                 "reference" : "     ",  "packed" : "     a001512",
                 "sigma_1" : 0.200000,
                 "sigma_2" : 0.200000,
                 "normalized_resid_1" : 0.225746,
                 "normalized_resid_2" : -0.090875,
                 "posn_sigma_theta" : 0.000000,
                 "RAMotion" : -0.5455,
                 "decMotion" : -0.0615,
                 "TotalMotion" : 0.5490,
                 "PAMotion" : 263.57, "dMag" : 0.04, "MagObs" : 20.40,
                 "MagBand" : "w", "MagSigma" : 0.5000,
                 "net" : " ",
                 "note1" : " ",
                 "note2" : "C",
                 "discovery_asterisk" : " ",
                 "flags" : 0,
                 "incl" : 1,
                 "ecliptic_lon" : 326.457688,
                 "ecliptic_lat" : 1.219253,
                 "earth_ecliptic_lon" : 330.405527 },
          {"JD": 2459813.950303, "iso date": "2022-08-22T10:48:26.179Z", "obscode": "F51",
                 "RA" : 328.264546, "Dec": -11.550164,
                 "dRA" : -0.0254, "dDec": 0.0097, "dTime": 2.643, "cross": 0.0124,
                 "reference" : "     ",  "packed" : "     a001512",
                 "sigma_1" : 0.200000,
                 "sigma_2" : 0.200000,
                 "normalized_resid_1" : -0.120733,
                 "normalized_resid_2" : -0.062211,
                 "posn_sigma_theta" : 0.000000,
                 "RAMotion" : -0.5454,
                 "decMotion" : -0.0612,
                 "TotalMotion" : 0.5488,
                 "PAMotion" : 263.60, "dMag" : -0.06, "MagObs" : 20.30,
                 "MagBand" : "w", "MagSigma" : 0.5000,
                 "net" : " ",
                 "note1" : " ",
                 "note2" : "C",
                 "discovery_asterisk" : " ",
                 "flags" : 0,
                 "incl" : 1,
                 "ecliptic_lon" : 326.455009,
                 "ecliptic_lat" : 1.219888,
                 "earth_ecliptic_lon" : 330.417809 },
          {"JD": 2459821.865114, "iso date": "2022-08-30T08:45:45.849Z", "obscode": "F52",
                 "RA" : 326.594921, "Dec": -11.736953,
                 "dRA" : 0.0505, "dDec": -0.0514, "dTime": -5.128, "cross": -0.0565,
                 "reference" : "     ",  "packed" : "     a001512",
                 "sigma_1" : 0.200000,
                 "sigma_2" : 0.200000,
                 "normalized_resid_1" : 0.223468,
                 "normalized_resid_2" : 0.282676,
                 "posn_sigma_theta" : 0.000000,
                 "RAMotion" : -0.5204,
                 "decMotion" : -0.0560,
                 "TotalMotion" : 0.5234,
                 "PAMotion" : 263.86, "dMag" : -0.08, "MagObs" : 20.50,
                 "MagBand" : "w", "MagSigma" : 0.5000,
                 "net" : " ",
                 "note1" : " ",
                 "note2" : "C",
                 "discovery_asterisk" : " ",
                 "flags" : 0,
                 "incl" : 1,
                 "ecliptic_lon" : 324.851296,
                 "ecliptic_lat" : 1.592234,
                 "earth_ecliptic_lon" : 338.218719 },
          {"JD": 2459821.877239, "iso date": "2022-08-30T09:03:13.449Z", "obscode": "F52",
                 "RA" : 326.592321, "Dec": -11.737189,
                 "dRA" : -0.0351, "dDec": 0.0705, "dTime": 3.141, "cross": 0.0738,
                 "reference" : "     ",  "packed" : "     a001512",
                 "sigma_1" : 0.200000,
                 "sigma_2" : 0.200000,
                 "normalized_resid_1" : -0.136921,
                 "normalized_resid_2" : -0.369002,
                 "posn_sigma_theta" : 0.000000,
                 "RAMotion" : -0.5206,
                 "decMotion" : -0.0557,
                 "TotalMotion" : 0.5236,
                 "PAMotion" : 263.89, "dMag" : 0.02, "MagObs" : 20.60,
                 "MagBand" : "w", "MagSigma" : 0.5000,
                 "net" : " ",
                 "note1" : " ",
                 "note2" : "C",
                 "discovery_asterisk" : " ",
                 "flags" : 0,
                 "incl" : 1,
                 "ecliptic_lon" : 324.848815,
                 "ecliptic_lat" : 1.592857,
                 "earth_ecliptic_lon" : 338.230670 },
          {"JD": 2459821.889442, "iso date": "2022-08-30T09:20:47.788Z", "obscode": "F52",
                 "RA" : 326.589733, "Dec": -11.737483,
                 "dRA" : -0.0155, "dDec": -0.0168, "dTime": 1.972, "cross": -0.0151,
                 "reference" : "     ",  "packed" : "     a001512",
                 "sigma_1" : 0.200000,
                 "sigma_2" : 0.200000,
                 "normalized_resid_1" : -0.085976,
                 "normalized_resid_2" : 0.075259,
                 "posn_sigma_theta" : 0.000000,
                 "RAMotion" : -0.5207,
                 "decMotion" : -0.0554,
                 "TotalMotion" : 0.5236,
                 "PAMotion" : 263.93, "dMag" : -0.08, "MagObs" : 20.50,
                 "MagBand" : "w", "MagSigma" : 0.5000,
                 "net" : " ",
                 "note1" : " ",
                 "note2" : "C",
                 "discovery_asterisk" : " ",
                 "flags" : 0,
                 "incl" : 1,
                 "ecliptic_lon" : 324.846327,
                 "ecliptic_lat" : 1.593421,
                 "earth_ecliptic_lon" : 338.242697 } 
        ]
      }
    }
  }
}
